onvif2/__init__.py
onvif2/cli.py
onvif2/client.py
onvif2/definition.py
onvif2/exceptions.py
onvif2/version.txt
onvif2_zeep-0.3.4.data/data/Lib/site-packages/wsdl/accesscontrol.wsdl
onvif2_zeep-0.3.4.data/data/Lib/site-packages/wsdl/accessrules.wsdl
onvif2_zeep-0.3.4.data/data/Lib/site-packages/wsdl/actionengine.wsdl
onvif2_zeep-0.3.4.data/data/Lib/site-packages/wsdl/advancedsecurity.wsdl
onvif2_zeep-0.3.4.data/data/Lib/site-packages/wsdl/analytics.wsdl
onvif2_zeep-0.3.4.data/data/Lib/site-packages/wsdl/analyticsdevice.wsdl
onvif2_zeep-0.3.4.data/data/Lib/site-packages/wsdl/appmgmt.wsdl
onvif2_zeep-0.3.4.data/data/Lib/site-packages/wsdl/authenticationbehavior.wsdl
onvif2_zeep-0.3.4.data/data/Lib/site-packages/wsdl/b-2.xsd
onvif2_zeep-0.3.4.data/data/Lib/site-packages/wsdl/bf-2.xsd
onvif2_zeep-0.3.4.data/data/Lib/site-packages/wsdl/bw-2-vs-mod.wsdl
onvif2_zeep-0.3.4.data/data/Lib/site-packages/wsdl/bw-2.wsdl
onvif2_zeep-0.3.4.data/data/Lib/site-packages/wsdl/common.xsd
onvif2_zeep-0.3.4.data/data/Lib/site-packages/wsdl/credential.wsdl
onvif2_zeep-0.3.4.data/data/Lib/site-packages/wsdl/deviceio.wsdl
onvif2_zeep-0.3.4.data/data/Lib/site-packages/wsdl/devicemgmt.wsdl
onvif2_zeep-0.3.4.data/data/Lib/site-packages/wsdl/devicemgmt.xml
onvif2_zeep-0.3.4.data/data/Lib/site-packages/wsdl/display.wsdl
onvif2_zeep-0.3.4.data/data/Lib/site-packages/wsdl/doorcontrol.wsdl
onvif2_zeep-0.3.4.data/data/Lib/site-packages/wsdl/event-vs.wsdl
onvif2_zeep-0.3.4.data/data/Lib/site-packages/wsdl/event.wsdl
onvif2_zeep-0.3.4.data/data/Lib/site-packages/wsdl/federated_search_documentation.html
onvif2_zeep-0.3.4.data/data/Lib/site-packages/wsdl/federatedsearch.wsdl
onvif2_zeep-0.3.4.data/data/Lib/site-packages/wsdl/fedsearch-docu-viewer.xsl
onvif2_zeep-0.3.4.data/data/Lib/site-packages/wsdl/humanbody.xsd
onvif2_zeep-0.3.4.data/data/Lib/site-packages/wsdl/humanface.xsd
onvif2_zeep-0.3.4.data/data/Lib/site-packages/wsdl/imaging.wsdl
onvif2_zeep-0.3.4.data/data/Lib/site-packages/wsdl/include
onvif2_zeep-0.3.4.dist-info/LICENSE
onvif2_zeep-0.3.4.dist-info/METADATA
onvif2_zeep-0.3.4.dist-info/WHEEL
onvif2_zeep-0.3.4.dist-info/entry_points.txt
onvif2_zeep-0.3.4.dist-info/top_level.txt
onvif2_zeep-0.3.4.dist-info/RECORD
