Metadata-Version: 2.1
Name: onvif2-zeep
Version: 0.3.4
Summary: Python Client for ONVIF2 Camera
Home-page: http://github.com/yingchengpa/python-onvif2
Author: Cheng Ying
Author-email: yingchengpa@qq.com
Maintainer: city
Maintainer-email: yingchengpa@qq.com
License: MIT
Keywords: ONVIF,Camera,IPC
Platform: UNKNOWN
License-File: LICENSE
Requires-Dist: zeep (>=3.0.0)
